decisionrules/__init__.py
decisionrules/custom_domain.py
decisionrules/decisionrules.py
decisionrules/dr_management.py
decisionrules/enums.py
decisionrules/exceptions.py
decisionrulespy-3.0.5.dist-info/LICENSE
decisionrulespy-3.0.5.dist-info/METADATA
decisionrulespy-3.0.5.dist-info/WHEEL
decisionrulespy-3.0.5.dist-info/top_level.txt
decisionrulespy-3.0.5.dist-info/RECORD
