Metadata-Version: 2.1
Name: decisionrulespy
Version: 3.0.5
Summary: A simple library for simple connecting to DecisionRules API
Home-page: https://github.com/decisionrules/decisionrulespy
Author: DecisionRules
Author-email: sales@decisionrules.io
Project-URL: Bug Tracker, https://github.com/decisionrules/decisionrulespy/issues
Project-URL: Docs, https://docs.decisionrules.io/docs/
Keywords: 'decisionrules rule solver rule_engine decision'
Classifier: Programming Language :: Python :: 3
Classifier: License :: OSI Approved :: MIT License
Classifier: Operating System :: OS Independent
Requires-Python: >=3.6
License-File: LICENSE
